main.py
jyyslide_md/__init__.py
jyyslide_md/converter.py
jyyslide_md/settings.py
jyyslide_md/static/css/base.css
jyyslide_md/static/css/tailwind.min.css
jyyslide_md/static/jyy/jyy.css
jyyslide_md/static/katex/auto-render.min.js
jyyslide_md/static/katex/katex.min.css
jyyslide_md/static/katex/katex.min.js
jyyslide_md/static/reveal/reveal.css
jyyslide_md/static/reveal/reveal.js
jyyslide_md/static/reveal/plugin/countdown.js
jyyslide_md/static/reveal/theme/simple.css
jyyslide_md/static/template/authortemp.html
jyyslide_md/static/template/basetemp.html
jyyslide_md/util/__init__.py
jyyslide_md/util/file_util.py
jyyslide_md/util/md_util.py
jyyslide_md/util/mdx_math.py
jyyslide_md/util/str_util.py
jyyslide_md-0.1.3.dist-info/LICENSE
jyyslide_md-0.1.3.dist-info/METADATA
jyyslide_md-0.1.3.dist-info/WHEEL
jyyslide_md-0.1.3.dist-info/entry_points.txt
jyyslide_md-0.1.3.dist-info/top_level.txt
jyyslide_md-0.1.3.dist-info/RECORD
