Metadata-Version: 2.2
Name: jyyslide-md
Version: 0.1.3
Summary: A Markdown tool for generating slides.
Author-email: zweix123 <1979803044@qq.com>, Qi-Zhan <qizhan@zju.edu.cn>
License: The MIT License (MIT)
Project-URL: Homepage, https://github.com/Qi-Zhan/jyyslide-md
Project-URL: Source, https://github.com/Qi-Zhan/jyyslide-md
Requires-Python: >=3.9
License-File: LICENSE
Requires-Dist: jinja2==3.1.4
Requires-Dist: markdown==3.4.1
Requires-Dist: pyquery==2.0.0
Requires-Dist: pygments==2.14.0
Requires-Dist: lxml==5.3.0
Requires-Dist: pyyaml==6.0.2
Requires-Dist: livereload
